README.md
pyproject.toml
setup.py
pycdr/__init__.py
pycdr/machinery.py
pycdr/main.py
pycdr/type_helper.py
pycdr/types.py
pycdr.egg-info/PKG-INFO
pycdr.egg-info/SOURCES.txt
pycdr.egg-info/dependency_links.txt
pycdr.egg-info/top_level.txt
pycdr/type_object/__init__.py
pycdr/type_object/builder.py
pycdr/type_object/idl_entities.py
pycdr/type_object/util.py