Metadata-Version: 2.1
Name: pycdr
Version: 0.1.4
Summary: Python CDR serialization
Home-page: https://github.com/thijsmie/cdds-py
Author: Thijs Miedema
Author-email: thijs.miedema@adlinktech.com
License: UNKNOWN
Project-URL: Bug Tracker, https://github.com/thijsmie/cdds-py/issues
Platform: UNKNOWN
Classifier: Development Status :: 4 - Beta
Classifier: License :: OSI Approved :: Eclipse Public License 2.0 (EPL-2.0)
Classifier: Programming Language :: Python :: 3.6
Classifier: Programming Language :: Python :: 3.7
Classifier: Programming Language :: Python :: 3.8
Classifier: Programming Language :: Python :: 3.9
Classifier: Programming Language :: Python :: 3.10
Classifier: Operating System :: OS Independent
Requires-Python: >=3.6
